{
    "_links": {
        "self": {
            "href": "http:\/\/default\/media\/4?_format=hal_json"
        },
        "type": {
            "href": "http:\/\/drupal.org\/rest\/type\/media\/fut_image"
        },
        "http:\/\/drupal.org\/rest\/relation\/media\/fut_image\/uid": [
            {
                "href": "http:\/\/default\/user\/1?_format=hal_json",
                "lang": "und"
            }
        ],
        "http:\/\/drupal.org\/rest\/relation\/media\/fut_image\/thumbnail": [
            {
                "href": "http:\/\/default\/sites\/default\/files\/2019-05\/post-2.jpg",
                "lang": "und"
            }
        ],
        "http:\/\/drupal.org\/rest\/relation\/media\/fut_image\/field_media_image": [
            {
                "href": "http:\/\/default\/sites\/default\/files\/2019-05\/post-2.jpg"
            }
        ]
    },
    "mid": [
        {
            "value": 4
        }
    ],
    "uuid": [
        {
            "value": "1d542789-7f9b-40c5-bcb8-33d8681afcfa"
        }
    ],
    "vid": [
        {
            "value": 4
        }
    ],
    "langcode": [
        {
            "value": "und",
            "lang": "und"
        }
    ],
    "bundle": [
        {
            "target_id": "fut_image"
        }
    ],
    "revision_created": [
        {
            "value": "2019-05-28T08:48:50+00:00",
            "format": "Y-m-d\\TH:i:sP"
        }
    ],
    "status": [
        {
            "value": true,
            "lang": "und"
        }
    ],
    "_embedded": {
        "http:\/\/drupal.org\/rest\/relation\/media\/fut_image\/uid": [
            {
                "_links": {
                    "self": {
                        "href": "http:\/\/default\/user\/1?_format=hal_json"
                    },
                    "type": {
                        "href": "http:\/\/drupal.org\/rest\/type\/user\/user"
                    }
                },
                "uuid": [
                    {
                        "value": "0d79d26c-29c8-4c71-bb6b-53344c1cad8b"
                    }
                ],
                "lang": "und"
            }
        ],
        "http:\/\/drupal.org\/rest\/relation\/media\/fut_image\/thumbnail": [
            {
                "_links": {
                    "self": {
                        "href": "http:\/\/default\/sites\/default\/files\/2019-05\/post-2.jpg"
                    },
                    "type": {
                        "href": "http:\/\/drupal.org\/rest\/type\/file\/file"
                    }
                },
                "uuid": [
                    {
                        "value": "d6c50cde-4b30-477c-b3f0-2dc84fbcceed"
                    }
                ],
                "lang": "und"
            }
        ],
        "http:\/\/drupal.org\/rest\/relation\/media\/fut_image\/field_media_image": [
            {
                "_links": {
                    "self": {
                        "href": "http:\/\/default\/sites\/default\/files\/2019-05\/post-2.jpg"
                    },
                    "type": {
                        "href": "http:\/\/drupal.org\/rest\/type\/file\/file"
                    }
                },
                "uuid": [
                    {
                        "value": "d6c50cde-4b30-477c-b3f0-2dc84fbcceed"
                    }
                ]
            }
        ]
    },
    "name": [
        {
            "value": "Post 2",
            "lang": "und"
        }
    ],
    "created": [
        {
            "value": "2019-05-28T08:48:24+00:00",
            "lang": "und",
            "format": "Y-m-d\\TH:i:sP"
        }
    ],
    "changed": [
        {
            "value": "2019-05-28T08:48:50+00:00",
            "lang": "und",
            "format": "Y-m-d\\TH:i:sP"
        }
    ],
    "default_langcode": [
        {
            "value": true,
            "lang": "und"
        }
    ],
    "revision_translation_affected": [
        {
            "value": true,
            "lang": "und"
        }
    ]
}